{"type":"Topology","objects":{"t14":{"type":"GeometryCollection","bbox":[120.17122741894113,23.077590934037033,120.24161204773424,23.153078783722698],"geometries":[{"type":"Polygon","properties":{"ID":null,"OBJECTID_1":4653,"VILLAGE":"後營里","TOWN":"西港區","COUNTY":"臺南市","VILLAGE_ID":"005","TOWN_ID":"67000140","COUNTY_ID":"67000","TV_ALL":"西港區後營里","VILLCODE":"A6714-005-00","ORI_VILLAG":null,"AREA":1516456.0867,"MAX_X":170868.6691,"MAX_Y":2561447.5305,"MIN_X":169505.7069,"MIN_Y":2558985.0511,"X":170124.5846,"Y":2560284.7367,"V_ID":"67000140-005","SORT":4,"COUNTYNAME":null,"TOWNNAME":null,"OBJECTID":0,"ORIG_FID":0,"Shape_Leng":0,"Shape_Le_1":7406.24437534,"Shape_Area":1516456.04072,"ET_ID":4651},"arcs":[[0,1,2,3]]},{"type":"Polygon","properties":{"ID":null,"OBJECTID_1":4656,"VILLAGE":"營西里","TOWN":"西港區","COUNTY":"臺南市","VILLAGE_ID":"006","TOWN_ID":"67000140","COUNTY_ID":"67000","TV_ALL":"西港區營西里","VILLCODE":"A6714-006-00","ORI_VILLAG":null,"AREA":3372809.155,"MAX_X":169872.2927,"MAX_Y":2561154.3789,"MIN_X":167257.5228,"MIN_Y":2558859.0414,"X":168793.4239,"Y":2560109.9084,"V_ID":"67000140-006","SORT":4,"COUNTYNAME":null,"TOWNNAME":null,"OBJECTID":0,"ORIG_FID":0,"Shape_Leng":0,"Shape_Le_1":9090.48024501,"Shape_Area":3372809.18751,"ET_ID":4654},"arcs":[[-3,4,5,6]]},{"type":"Polygon","properties":{"ID":null,"OBJECTID_1":4690,"VILLAGE":"西港里","TOWN":"西港區","COUNTY":"臺南市","VILLAGE_ID":"001","TOWN_ID":"67000140","COUNTY_ID":"67000","TV_ALL":"西港區西港里","VILLCODE":"A6714-001-00","ORI_VILLAG":null,"AREA":1940582.9278,"MAX_X":169288.8467,"MAX_Y":2560448.9543,"MIN_X":167232.2571,"MIN_Y":2556524.1808,"X":168629.1274,"Y":2558293.5192,"V_ID":"67000140-001","SORT":4,"COUNTYNAME":null,"TOWNNAME":null,"OBJECTID":0,"ORIG_FID":0,"Shape_Leng":0,"Shape_Le_1":10599.5740258,"Shape_Area":1940582.9543,"ET_ID":4688},"arcs":[[7,-6,8,9,10,11]]},{"type":"Polygon","properties":{"ID":null,"OBJECTID_1":4700,"VILLAGE":"南海里","TOWN":"西港區","COUNTY":"臺南市","VILLAGE_ID":"002","TOWN_ID":"67000140","COUNTY_ID":"67000","TV_ALL":"西港區南海里","VILLCODE":"A6714-002-00","ORI_VILLAG":null,"AREA":3982420.8138,"MAX_X":168544.3837,"MAX_Y":2557972.2087,"MIN_X":166651.7391,"MIN_Y":2554276.3154,"X":167535.4582,"Y":2556290.1232,"V_ID":"67000140-002","SORT":4,"COUNTYNAME":null,"TOWNNAME":null,"OBJECTID":0,"ORIG_FID":0,"Shape_Leng":0,"Shape_Le_1":9737.15221583,"Shape_Area":3982420.79098,"ET_ID":4698},"arcs":[[-11,12,13,14,15]]},{"type":"Polygon","properties":{"ID":null,"OBJECTID_1":4701,"VILLAGE":"劉厝里","TOWN":"西港區","COUNTY":"臺南市","VILLAGE_ID":"008","TOWN_ID":"67000140","COUNTY_ID":"67000","TV_ALL":"西港區劉厝里","VILLCODE":"A6714-008-00","ORI_VILLAG":null,"AREA":1962677.4167,"MAX_X":166492.8665,"MAX_Y":2560152.1154,"MIN_X":165114.8051,"MIN_Y":2557611.1712,"X":165908.9274,"Y":2558875.9459,"V_ID":"67000140-008","SORT":4,"COUNTYNAME":null,"TOWNNAME":null,"OBJECTID":0,"ORIG_FID":0,"Shape_Leng":0,"Shape_Le_1":7367.73857022,"Shape_Area":1962677.41169,"ET_ID":4699},"arcs":[[16,17,18,19]]},{"type":"Polygon","properties":{"ID":null,"OBJECTID_1":4716,"VILLAGE":"港東里","TOWN":"西港區","COUNTY":"臺南市","VILLAGE_ID":"003","TOWN_ID":"67000140","COUNTY_ID":"67000","TV_ALL":"西港區港東里","VILLCODE":"A6714-003-00","ORI_VILLAG":null,"AREA":2617944.2018,"MAX_X":170843.1778,"MAX_Y":2559133.7289,"MIN_X":168829.4183,"MIN_Y":2556920.0153,"X":169706.1962,"Y":2558121.2869,"V_ID":"67000140-003","SORT":4,"COUNTYNAME":null,"TOWNNAME":null,"OBJECTID":0,"ORIG_FID":0,"Shape_Leng":0,"Shape_Le_1":7214.90936721,"Shape_Area":2617944.20571,"ET_ID":4714},"arcs":[[-2,20,21,-9,-5]]},{"type":"Polygon","properties":{"ID":null,"OBJECTID_1":4723,"VILLAGE":"竹林里","TOWN":"西港區","COUNTY":"臺南市","VILLAGE_ID":"009","TOWN_ID":"67000140","COUNTY_ID":"67000","TV_ALL":"西港區竹林里","VILLCODE":"A6714-009-00","ORI_VILLAG":null,"AREA":1645609.7263,"MAX_X":167295.9241,"MAX_Y":2559021.0271,"MIN_X":166011.1339,"MIN_Y":2556967.9975,"X":166580.7729,"Y":2557981.9985,"V_ID":"67000140-009","SORT":4,"COUNTYNAME":null,"TOWNNAME":null,"OBJECTID":0,"ORIG_FID":0,"Shape_Leng":0,"Shape_Le_1":5778.48440037,"Shape_Area":1645609.72929,"ET_ID":4721},"arcs":[[-15,22,-18,23]]},{"type":"Polygon","properties":{"ID":null,"OBJECTID_1":4731,"VILLAGE":"■林里","TOWN":"西港區","COUNTY":"臺南市","VILLAGE_ID":"004","TOWN_ID":"67000140","COUNTY_ID":"67000","TV_ALL":"西港區■林里","VILLCODE":"A6714-004-00","ORI_VILLAG":null,"AREA":3112109.6101,"MAX_X":172329.6094,"MAX_Y":2560685.9426,"MIN_X":170064.1659,"MIN_Y":2558180,"X":171147.5647,"Y":2559394.1832,"V_ID":"67000140-004","SORT":4,"COUNTYNAME":null,"TOWNNAME":null,"OBJECTID":0,"ORIG_FID":0,"Shape_Leng":0,"Shape_Le_1":8516.9696203,"Shape_Area":3112109.64655,"ET_ID":4729},"arcs":[[24,-21,-1]]},{"type":"Polygon","properties":{"ID":null,"OBJECTID_1":4733,"VILLAGE":"慶安里","TOWN":"西港區","COUNTY":"臺南市","VILLAGE_ID":"012","TOWN_ID":"67000140","COUNTY_ID":"67000","TV_ALL":"西港區慶安里","VILLCODE":"A6714-012-00","ORI_VILLAG":null,"AREA":3720209.031,"MAX_X":168497.7509,"MAX_Y":2560588.3474,"MIN_X":166423.3798,"MIN_Y":2556580.0477,"X":167490.8688,"Y":2558860.2434,"V_ID":"67000140-012","SORT":4,"COUNTYNAME":null,"TOWNNAME":null,"OBJECTID":0,"ORIG_FID":0,"Shape_Leng":0,"Shape_Le_1":10707.1691688,"Shape_Area":3720209.02709,"ET_ID":4731},"arcs":[[-12,-16,-24,-17,25]]},{"type":"Polygon","properties":{"ID":null,"OBJECTID_1":4788,"VILLAGE":"新復里","TOWN":"西港區","COUNTY":"臺南市","VILLAGE_ID":"011","TOWN_ID":"67000140","COUNTY_ID":"67000","TV_ALL":"西港區新復里","VILLCODE":"A6714-011-00","ORI_VILLAG":null,"AREA":3150367.6754,"MAX_X":167273.7669,"MAX_Y":2557676.8861,"MIN_X":165518.3558,"MIN_Y":2553109.75,"X":166506.1202,"Y":2555385.1834,"V_ID":"67000140-011","SORT":4,"COUNTYNAME":null,"TOWNNAME":null,"OBJECTID":0,"ORIG_FID":0,"Shape_Leng":0,"Shape_Le_1":12539.7130574,"Shape_Area":3150367.68336,"ET_ID":4786},"arcs":[[-23,-14,26,27,28,-19]]},{"type":"Polygon","properties":{"ID":null,"OBJECTID_1":4800,"VILLAGE":"永樂里","TOWN":"西港區","COUNTY":"臺南市","VILLAGE_ID":"010","TOWN_ID":"67000140","COUNTY_ID":"67000","TV_ALL":"西港區永樂里","VILLCODE":"A6714-010-00","ORI_VILLAG":null,"AREA":2573602.7499,"MAX_X":166371.3729,"MAX_Y":2556837.608,"MIN_X":165192.1369,"MIN_Y":2553141.5,"X":165829.8394,"Y":2554969.3707,"V_ID":"67000140-010","SORT":4,"COUNTYNAME":null,"TOWNNAME":null,"OBJECTID":0,"ORIG_FID":0,"Shape_Leng":0,"Shape_Le_1":9754.1802767,"Shape_Area":2573602.78341,"ET_ID":4798},"arcs":[[29,-28]]}]}},"arcs":[[[7960,9092],[-38,-21],[-8,-5],[-396,-224],[-7,-6],[103,-98],[-306,-167],[-65,-63],[88,-85],[-68,-38],[-8,-5],[43,-57],[71,-95],[-514,-289],[-4,-2],[8,-3],[289,-113],[32,-13],[-2,-5],[-2,-4],[-36,-133],[-29,-111],[-68,-256],[-61,-246]],[[6982,7053],[-369,71],[-326,63],[-204,40],[-2,0]],[[6081,7227],[6,9],[6,11],[13,31],[63,163],[9,25],[161,-30],[62,257],[28,113],[143,126],[-47,13],[-19,6],[-139,39],[20,54],[6,15],[7,11],[12,14],[26,28],[4,4],[15,13],[21,20],[2,1],[15,12],[-17,29],[-7,11],[-1,5],[3,41],[6,35],[3,35],[0,31],[-1,29],[-32,29],[-27,15],[-17,9],[6,33],[14,73],[9,42],[2,4],[2,5],[19,5],[1,1],[18,7],[104,41],[1,0],[-1,7],[-3,18],[-13,89],[-8,50],[-4,29],[0,5],[-1,20],[-1,13],[-5,24],[-2,15],[-4,28],[-5,50],[-8,63],[-9,79],[-21,202],[-6,54],[-25,258]],[[6465,9646],[-12,115],[-13,123],[4,1],[33,-2],[27,-6],[24,-8],[11,-7],[6,-6],[7,-5],[9,-12],[11,-16],[15,-27],[26,-54],[17,8],[384,237],[14,10],[3,2],[44,-36],[67,-53],[12,-11],[2,-1],[104,-105],[22,-24],[47,-21],[104,-108],[171,-218],[115,-112],[102,-96],[48,-45],[39,-36],[52,-41]],[[6081,7227],[-9,-15],[-18,-22],[-156,-167],[-14,-15],[-102,-111]],[[5782,6897],[-117,93],[-79,82],[-125,130],[-124,127],[-61,64],[-6,8],[-37,38],[-86,88],[-58,61],[-27,27],[-158,164],[-122,-85],[-363,-261],[-69,-49],[-13,-9],[-1,-1],[-29,-21],[-8,-6],[-16,14],[-32,33],[-27,25],[-107,116],[-4,4],[-41,48],[-42,49],[-81,88],[-108,120],[-41,44],[-48,49],[-14,14],[-71,75],[-41,40],[-52,54],[-8,11],[-92,94],[-36,35],[-33,35],[-26,26],[-55,56],[-79,87],[-50,51],[-35,37],[-83,86],[-48,49],[-76,98]],[[2953,8785],[98,58],[74,44],[17,9],[47,15],[102,32],[109,33],[93,29],[88,27],[92,29],[134,43],[97,29],[93,29],[93,30],[83,25],[26,8],[93,30],[99,30],[27,8],[105,33],[143,44],[47,15],[2,1],[1,0],[1,-6],[10,-33],[34,-105],[76,-242],[3,1],[43,9],[349,84],[258,60],[9,2],[4,1],[-17,49],[-35,112],[-3,12],[-4,20],[-10,54],[7,1],[1021,240],[3,1]],[[2938,8777],[15,8]],[[5782,6897],[-45,-50],[-52,-56],[-2,-3],[-55,-57],[-31,-37],[-10,-13],[-11,-12],[-31,-39],[-36,-48],[18,-4],[15,-1],[34,1],[-18,-29],[-66,-109],[-19,-31],[-90,-153],[-29,-47],[-53,-88],[-43,-70],[-25,-48],[-12,-26],[-70,13],[25,-131],[27,-124],[18,-64],[35,-145],[8,3],[3,0],[9,-47],[5,-28],[3,-22],[0,-25],[-3,-31],[-1,-62],[-4,-67],[-1,-44],[-2,-6],[-3,-11],[-4,-35],[-6,-25],[-8,-26],[-6,-13],[-11,-24],[-3,-7],[-15,-25],[-13,-17],[-31,-38],[-14,-14],[2,0],[325,-64],[5,-4],[6,-4],[11,-20],[10,-16],[164,-277]],[[5682,4577],[-11,-7],[-40,-26],[-46,-29],[-23,-12],[-58,-31],[-65,-33],[-49,-26],[-23,-11],[-130,-8],[-14,-8],[-67,-42],[-113,-73],[-107,-67],[-94,-58],[-68,-42],[-6,-4]],[[4768,4100],[-118,237],[-11,22]],[[4639,4359],[-7,14],[-19,38],[-10,49],[-4,29],[-4,58],[0,1],[1,2],[14,23],[47,187],[10,35],[21,74],[4,23],[5,33],[0,2],[1,20],[-4,17],[-23,132],[-12,96],[-6,50],[-8,56],[-9,61],[-35,218],[-4,25],[-3,20],[-5,28],[-9,53],[-4,22],[-12,61],[-16,82],[-8,41],[-6,29],[-2,27],[-16,217],[-1,9],[-3,22],[-8,27],[-3,15],[-18,73],[-2,6],[-57,152],[-60,159],[-3,9],[-39,109],[-27,72],[-19,49],[-11,30],[-17,46],[-10,25],[-12,35],[-33,65],[-37,74],[-5,12],[-17,34],[-48,97],[-3,7],[-19,39],[-28,61],[-18,30],[-11,17],[-19,27],[-9,11],[-21,24],[-46,44],[-1,1],[-13,12],[-15,14],[-47,47],[-38,42],[-96,125],[-7,8],[-64,79],[-120,146],[-1,1],[-30,36],[-58,72],[-86,109],[-41,51],[-130,162],[-64,78],[-38,45],[-77,94],[-68,81],[20,12]],[[4768,4100],[-1,-1],[-18,-11],[-75,-48],[-101,-61],[-92,-57],[6,-99],[4,-164],[7,-145],[0,-10],[5,-136],[6,-153],[5,-118],[-30,-13],[37,-74],[50,-99],[-331,-109],[-18,-31],[-8,-14],[-40,-70],[-26,-64],[-52,-89],[-206,-292],[-79,-111],[-35,-50],[-98,-89],[-84,-75],[-26,-23],[-209,-188],[-91,-82],[-245,-221]],[[3023,1403],[-3,2],[-7,4],[-3,4],[-2,8],[-3,15],[-15,76],[-5,37],[-5,33],[-13,70],[-12,47],[-5,40],[-7,54],[-8,61],[-3,29],[-2,17],[-2,17],[-16,104],[-38,299],[-5,35],[-7,45],[-3,24],[-2,10],[-67,175],[-9,31],[-7,28],[-42,227],[-19,40],[-35,38],[-71,78],[-110,143],[-108,145],[-44,82],[-30,80],[-7,35],[-11,45],[-14,82],[-20,140],[-13,79],[-6,31],[-14,78],[-7,43],[-3,16],[-1,10],[-20,123],[-2,16],[-16,101],[0,1],[-18,99],[-15,111],[-8,29],[6,18],[90,253],[64,180],[4,17],[1,9],[0,4]],[[2305,5021],[178,69],[27,9],[36,13],[75,31],[35,16],[9,5],[9,4],[4,2],[-17,298],[71,3],[295,11],[-3,70],[-3,52]],[[3021,5604],[33,-6],[84,-15],[28,0],[54,9],[24,6],[53,13],[70,20],[35,8],[49,10],[31,8],[23,10],[33,19],[31,19],[19,12],[-3,63],[0,33],[0,1],[255,10],[55,3],[42,1],[0,-4],[1,-41],[1,-67],[3,-33],[2,-24],[7,-86],[0,-1],[-16,-172],[-6,-91],[31,-3],[16,-3],[9,-3],[19,-18],[18,-16],[12,-10],[9,-2],[1,-12],[10,-59],[6,-48],[4,-27],[41,-254],[6,-54],[7,-26],[1,-6],[30,-180],[9,-54],[24,-167],[14,-81],[3,-14],[15,-89],[3,-19],[88,41],[166,77],[61,25],[75,35],[29,15],[3,2]],[[1798,8425],[3,-7],[2,-9],[1,-1],[0,-5],[5,-26],[6,-53],[2,-15],[4,-31],[8,-55],[6,-40],[4,-34],[3,-25],[2,-60],[0,-6],[4,-62],[3,-72],[2,-28],[7,-151],[2,-31],[0,-1],[8,-144],[4,-75],[3,-49],[4,-120],[5,-82],[2,-38],[10,-213],[5,-73],[0,-2],[1,-28]],[[1904,6889],[0,-11],[0,-5],[0,-5],[-4,-23],[-4,-31],[-10,-49],[-8,-34],[-20,-94],[-24,-114],[-1,-16],[0,-13],[2,-55],[-1,-21],[-9,0],[-5,0],[-139,-3],[-160,-6],[-131,-7],[-138,-3],[-12,2],[0,-33],[0,-93],[1,-106],[0,-22],[3,-168],[1,-54],[0,-49],[6,-129],[4,-74],[7,-127],[6,-68],[1,-16]],[[1269,5462],[-662,-77],[-44,-5]],[[563,5380],[-9,9],[-40,40],[-226,170],[-288,218],[44,9],[434,48],[8,7],[0,14],[-12,137],[-3,63],[-4,33],[-2,12],[-7,249],[-1,40],[-5,215],[-4,53],[-20,310],[1,13],[1,17],[-11,152],[-15,250],[-17,252],[-5,124],[863,36],[11,124],[22,260],[3,35],[10,104],[0,1],[8,0],[23,1],[52,6],[110,8],[196,16],[27,3],[26,3],[29,5],[16,2],[14,4],[3,1],[3,1]],[[6982,7053],[1,0],[121,-23],[550,-108],[0,-1],[-16,-62],[-46,-180],[-26,-93],[-8,-30],[-62,-245],[-48,-177],[-5,-23],[-3,-18],[248,184],[21,-2],[3,-1],[21,-7],[54,-24],[50,-26],[63,-47],[42,-40],[1,-1]],[[7943,6129],[-4,-3],[-103,-78],[-5,-7],[-10,-7],[-55,-38],[-78,-55],[-107,-74],[-52,-37],[-77,-55],[-60,-42],[-84,-58],[-94,-65],[-41,-30],[-85,-74],[-79,-66],[-80,-71],[-45,-40],[-51,-45],[-33,-28],[-45,-35],[-36,-25],[-65,-47],[-56,-41],[-70,-50],[-30,-24],[-43,-24],[-32,-19],[-33,-16],[-51,-26],[-79,-37],[-61,-31],[-119,-69],[-60,-34],[-102,-59],[-80,-46],[-68,-39],[-74,-48],[-14,-9]],[[2305,5021],[-52,-18],[-141,-58],[-28,-12],[-59,-25],[-163,-68],[-181,-81],[-311,-139],[-13,-6],[-4,18],[-6,76],[-12,157],[-7,94],[-27,252],[-16,124],[-3,21],[-13,106]],[[1904,6889],[5,5],[14,12],[18,15],[17,18],[25,29],[27,23],[16,10],[21,10],[26,11],[23,8],[109,30],[24,7],[20,4],[23,3],[22,0],[30,-2],[20,-5],[21,-8],[30,-15],[43,-26],[18,-10],[17,-8],[4,-2],[8,-5],[4,-2],[2,-1],[35,-22],[41,-23],[9,-3],[1,-29],[6,-126],[5,-123],[1,-22],[1,-14],[1,-9],[5,-16],[11,-43],[13,-52],[7,-30],[5,-16],[4,-10],[10,-21],[16,-28],[4,-7],[5,-9],[9,-18],[10,-19],[8,-14],[5,-9],[8,-13],[2,-3],[0,-3],[24,-43],[27,-49],[31,-54],[44,-75],[4,-6],[2,-6],[2,-5],[1,-11],[-5,-25],[-4,-11],[-2,-5],[0,-1],[-10,-18],[-6,-15],[-4,-12],[-1,-17],[2,-21],[2,-17],[7,-17],[19,-33],[25,-53],[12,-26],[4,-7],[21,-46],[18,-45],[16,-32],[37,-40],[13,-8],[29,-6]],[[7960,9092],[4,-3],[49,-39],[41,-53],[57,-83],[34,-33],[1,-1],[101,-79],[51,-36],[24,-28],[18,-29],[42,-38],[39,-26],[78,-57],[3,-2],[17,-15],[16,-13],[12,-10],[34,-27],[38,-48],[3,-4],[6,-3],[122,-78],[30,-12],[34,-13],[12,-30],[8,-19],[18,-42],[1,0],[1,-1],[56,-32],[33,-18],[235,-135],[73,-37],[27,-15],[21,-12],[5,-4],[14,-8],[11,-14],[2,-6],[6,-12],[3,-10],[1,-18],[120,-8],[42,-3],[22,1],[12,0],[32,6],[10,2],[132,-57],[42,-16],[23,-6],[25,-7],[23,19],[25,21],[24,22],[54,-8],[66,-8],[0,-23],[1,-73],[1,-84],[0,-61],[0,-26],[1,-90],[0,-84],[1,-68],[-1,-82],[2,-61],[0,-34],[-1,-47],[2,-37],[-1,-61],[1,-35],[-9,-2],[-13,-4],[-27,-15],[-60,-25],[-26,-10],[-67,-28],[-54,-24],[-24,-11],[-50,-25],[-36,-24],[-28,-16],[-25,-15],[-24,-16],[-5,-3],[-8,-5],[-40,-15],[-35,-12],[-32,-10],[-43,-11],[-58,-19],[-45,-13],[-23,-1],[-55,-2],[-74,0],[-40,4],[-55,1],[-38,1],[-8,-2],[-10,-6],[-44,-21],[-53,-25],[-51,-21],[-21,-9],[-29,-11],[-14,-6],[-34,-14],[-73,-31],[-57,-25],[-83,-39],[-46,-26],[-8,-5],[-37,-20],[-73,-48],[-71,-46],[-9,-6],[-59,-43],[-15,-11],[-89,-65],[-178,-132]],[[1798,8425],[2,1],[7,1],[8,4],[8,3],[11,6],[17,9],[101,60],[60,36],[188,116],[20,12],[30,18],[53,32],[71,45],[52,32],[45,27],[29,17],[85,52],[20,12],[7,4],[7,3],[7,2],[23,2],[25,1],[24,0],[19,-1],[7,0],[7,1],[7,2],[3,3],[1,0],[6,4],[15,9],[11,7],[10,6],[154,-174]],[[3023,1403],[-189,-170],[-11,-10],[-232,-208],[-56,-51],[-252,-227],[6,-4],[4,-2],[-82,-72],[-111,-99],[-85,-72],[-97,-88],[-77,-71],[-39,-35],[-23,-21],[-33,-38],[-24,-24],[-22,-23],[0,1],[-123,-109],[-95,-80],[-45,81],[-20,22]],[[1417,103],[-14,33],[-20,38],[-13,11],[-19,7],[63,94],[45,84],[20,34],[19,34],[2,32],[7,41],[6,38],[-50,-6],[-76,-8],[-185,-17],[-3,0],[137,328],[74,152],[178,-38],[16,-4],[8,0],[140,-28],[0,11],[-27,143],[-2,26],[0,17],[4,8],[10,34],[5,32],[8,62],[15,69],[5,24],[0,14],[0,31],[1,7],[0,94],[-12,91],[-4,23],[-7,19],[-30,73],[-9,16],[-9,12],[-8,6],[-11,2],[-12,2],[-4,4],[-29,54],[-22,23],[-35,24],[-29,67],[-35,-17],[160,879],[-221,43],[-11,2],[6,80],[-2,32],[-1,22],[-8,248],[-12,104],[-5,146],[-5,104],[1,18],[-6,124],[-2,77],[-2,44],[-4,132],[-3,59],[-3,72],[-1,27],[-3,51],[-4,45],[-2,36],[-14,204],[0,10],[-156,-21],[-47,-5],[-27,-2],[-115,3],[-52,4]],[[976,4437],[-2,8],[-1,2],[-42,106],[-1,2],[-7,18],[-3,5],[-7,10],[-17,26],[-14,20],[-11,18],[-3,9],[-2,14],[-8,48],[-1,7],[-1,4],[-2,10],[-7,22],[-18,47],[-16,47],[-16,37],[-6,16],[-60,151],[-32,74],[-15,42],[-25,59],[-18,37],[-9,15],[-31,50],[-38,39]],[[1417,103],[-6,-2],[-115,-39],[-98,-25],[-46,12],[-75,18],[-24,8],[-27,5],[-29,-2],[-30,-3],[-13,0],[-11,4],[-8,9],[-4,21],[-98,-8],[-58,-5],[-26,-1],[-14,3],[-6,5],[-3,24],[-5,50],[-2,12],[3,5],[10,5],[6,5],[0,18],[2,55],[1,52],[-1,46],[-3,43],[-10,31],[-9,17],[-7,14],[-110,-11],[-50,-3],[-15,-1],[-119,176],[-34,42],[-5,5],[-9,-5],[-14,19],[-12,9],[-20,-15],[-61,51],[-53,43],[-3,1],[5,4],[12,9],[99,101],[6,5],[58,35],[17,11],[11,9],[19,21],[0,1],[21,26],[20,21],[10,9],[3,5],[3,7],[7,45],[2,5],[2,4],[-1,17],[-8,29],[-11,41],[-3,19],[-2,27],[-3,17],[0,22],[2,11],[6,12],[2,7],[4,16],[21,70],[9,28],[8,16],[32,113],[9,28],[5,17],[4,10],[6,18],[4,16],[9,34],[10,22],[5,11],[3,23],[1,35],[0,24],[2,31],[1,17],[3,17],[6,21],[5,28],[25,150],[10,91],[-11,66],[-3,14],[0,13],[0,25],[-8,116],[-2,51],[0,23],[-1,14],[4,32],[7,40],[15,92],[13,121],[1,3],[7,46],[-300,97],[-40,13],[-6,12],[-55,113],[-124,247],[-36,76],[-3,10],[34,8],[26,10],[19,15],[16,16],[12,17],[15,19],[29,42],[28,42],[28,40],[37,53],[26,39],[25,35],[29,43],[26,35],[25,36],[51,74],[26,38],[2,3],[27,40],[52,74],[36,53],[54,75],[56,79],[45,63],[33,49],[23,24],[11,7],[15,13],[36,19],[11,5]]],"transform":{"scale":[0.000007039166795990312,0.000007549539922558735],"translate":[120.17122741894113,23.077590934037033]}}